contrib/__init__.py
contrib/dose_rate.py
contrib/dose_rate_helpers.py
contrib/dose_rate_test1.json
contrib/gam_ge_nm670_spect.py
contrib/gam_iec_phantom.py
contrib/gam_linac.py
contrib/gam_linac_materials.db
contrib/gam_pet.py
contrib/ge_nm670_spect_materials.db
contrib/spect_iec_phsp.py
contrib/spect_iec_phsp_v2.py
contrib/spect_recon.py
contrib/dose_rate_data/29_CT_5mm.mhd
contrib/dose_rate_data/29_CT_5mm.raw
contrib/dose_rate_data/29_CT_5mm_crop.mhd
contrib/dose_rate_data/29_CT_5mm_crop.raw
contrib/dose_rate_data/385_NM_5mm.mhd
contrib/dose_rate_data/385_NM_5mm.raw
contrib/dose_rate_data/385_NM_5mm_crop.mhd
contrib/dose_rate_data/385_NM_5mm_crop.raw
contrib/dose_rate_data/Schneider2000DensitiesTable.txt
contrib/dose_rate_data/Schneider2000MaterialsTable.txt
contrib/dose_rate_data/activity_test.mhd
contrib/dose_rate_data/activity_test.raw
contrib/dose_rate_data/activity_test_crop.mhd
contrib/dose_rate_data/activity_test_crop.raw
contrib/dose_rate_data/activity_test_crop_4mm.mhd
contrib/dose_rate_data/activity_test_crop_4mm.raw
gam_gate/ActionManager.py
gam_gate/ExceptionHandler.py
gam_gate/RunAction.py
gam_gate/Simulation.py
gam_gate/SimulationUserInfo.py
gam_gate/UIsessionSilent.py
gam_gate/UIsessionVerbose.py
gam_gate/UserElement.py
gam_gate/UserInfo.py
gam_gate/__init__.py
gam_gate/gam_gate_info
gam_gate/gam_gate_user_info
gam_gate/helpers.py
gam_gate/helpers_element.py
gam_gate/helpers_image.py
gam_gate/helpers_log.py
gam_gate/helpers_physics.py
gam_gate/helpers_run_timing.py
gam_gate/helpers_tests.py
gam_gate/helpers_transform.py
gam_gate/actor/ActorBase.py
gam_gate/actor/ActorManager.py
gam_gate/actor/DoseActor.py
gam_gate/actor/FilterBase.py
gam_gate/actor/FilterManager.py
gam_gate/actor/HitsAdderActor.py
gam_gate/actor/HitsCollectionActor.py
gam_gate/actor/HitsEnergyWindowsActor.py
gam_gate/actor/HitsProjectionActor.py
gam_gate/actor/MotionVolumeActor.py
gam_gate/actor/ParticleFilter.py
gam_gate/actor/PhaseSpaceActor.py
gam_gate-0.3.5.dist-info/METADATA
gam_gate-0.3.5.dist-info/WHEEL
gam_gate-0.3.5.dist-info/top_level.txt
gam_gate-0.3.5.dist-info/RECORD
