Metadata-Version: 2.1
Name: gam-gate
Version: 0.3.5
Summary: Simulation for Medical Physics
Home-page: https://github.com/dsarrut/gam-gate
Author: Opengate collaboration
Author-email: david.sarrut@creatis.insa-lyon.fr
License: UNKNOWN
Platform: UNKNOWN
Classifier: Programming Language :: Python :: 3
Classifier: License :: OSI Approved :: Apache Software License
Classifier: Operating System :: OS Independent
Requires-Python: >=3.5
Requires-Dist: gam-g4 (==0.3.5)
Requires-Dist: gatetools
Requires-Dist: tqdm
Requires-Dist: colored
Requires-Dist: click
Requires-Dist: python-box
Requires-Dist: anytree
Requires-Dist: numpy
Requires-Dist: itk
Requires-Dist: uproot
Requires-Dist: sphinx
Requires-Dist: scipy
Requires-Dist: sphinx-pdj-theme
Requires-Dist: matplotlib
Requires-Dist: myst-parser
Requires-Dist: colorlog
